litenn_apps/__init__.py
litenn_apps/core/__init__.py
litenn_apps/recognition/face/__init__.py
litenn_apps/recognition/face/S3FD/S3FD.py
litenn_apps/recognition/face/S3FD/__init__.py
litenn_apps/test_data/__init__.py
litenn_apps/test_data/photo/__init__.py
litenn_apps/test_data/photo/multiple_faces.jpg
litenn_apps-2020.11.91.dist-info/METADATA
litenn_apps-2020.11.91.dist-info/WHEEL
litenn_apps-2020.11.91.dist-info/top_level.txt
litenn_apps-2020.11.91.dist-info/RECORD
