Metadata-Version: 2.1
Name: litenn-apps
Version: 2020.11.91
Summary: UNKNOWN
Home-page: https://github.com/iperov/litenn-apps
Author: iperov
Author-email: lepersorium@gmail.com
License: MIT
Platform: UNKNOWN
Classifier: License :: OSI Approved :: MIT License
Classifier: Operating System :: OS Independent
Classifier: Programming Language :: Python :: 3
Classifier: Environment :: GPU
Classifier: Topic :: Scientific/Engineering
Requires-Python: >=3.6
Requires-Dist: numpy
Requires-Dist: litenn
Requires-Dist: opencv-python
